{
  "Id": "bibarel",
  "DexId": 400,
  "RawIndex": 435,
  "Name": "Bibarel",
  "GameSeries": 1,
  "PrimaryType": 1,
  "SecondaryType": 3,
  "Category": "Beaver",
  "LevelStats": [
    {
      "RequiredExp": 0,
      "HP": 0,
      "Attack": 0,
      "Defense": 0,
      "SpecialAttack": 0,
      "SpecialDefense": 0
    },
    {
      "RequiredExp": 8,
      "HP": 1,
      "Attack": 1,
      "Defense": 1,
      "SpecialAttack": 1,
      "SpecialDefense": 1
    },
    {
      "RequiredExp": 20,
      "HP": 1,
      "Attack": 1,
      "Defense": 0,
      "SpecialAttack": 1,
      "SpecialDefense": 0
    },
    {
      "RequiredExp": 35,
      "HP": 1,
      "Attack": 0,
      "Defense": 1,
      "SpecialAttack": 0,
      "SpecialDefense": 1
    },
    {
      "RequiredExp": 77,
      "HP": 1,
      "Attack": 1,
      "Defense": 0,
      "SpecialAttack": 1,
      "SpecialDefense": 0
    },
    {
      "RequiredExp": 169,
      "HP": 1,
      "Attack": 0,
      "Defense": 1,
      "SpecialAttack": 0,
      "SpecialDefense": 1
    },
    {
      "RequiredExp": 262,
      "HP": 1,
      "Attack": 1,
      "Defense": 0,
      "SpecialAttack": 1,
      "SpecialDefense": 0
    },
    {
      "RequiredExp": 492,
      "HP": 1,
      "Attack": 1,
      "Defense": 1,
      "SpecialAttack": 1,
      "SpecialDefense": 1
    },
    {
      "RequiredExp": 992,
      "HP": 1,
      "Attack": 1,
      "Defense": 0,
      "SpecialAttack": 1,
      "SpecialDefense": 0
    },
    {
      "RequiredExp": 1494,
      "HP": 1,
      "Attack": 1,
      "Defense": 1,
      "SpecialAttack": 1,
      "SpecialDefense": 1
    },
    {
      "RequiredExp": 2284,
      "HP": 1,
      "Attack": 1,
      "Defense": 0,
      "SpecialAttack": 1,
      "SpecialDefense": 0
    },
    {
      "RequiredExp": 4216,
      "HP": 1,
      "Attack": 1,
      "Defense": 1,
      "SpecialAttack": 1,
      "SpecialDefense": 1
    },
    {
      "RequiredExp": 6152,
      "HP": 1,
      "Attack": 1,
      "Defense": 0,
      "SpecialAttack": 1,
      "SpecialDefense": 0
    },
    {
      "RequiredExp": 9592,
      "HP": 1,
      "Attack": 1,
      "Defense": 0,
      "SpecialAttack": 1,
      "SpecialDefense": 0
    },
    {
      "RequiredExp": 13035,
      "HP": 1,
      "Attack": 1,
      "Defense": 1,
      "SpecialAttack": 1,
      "SpecialDefense": 1
    },
    {
      "RequiredExp": 16895,
      "HP": 1,
      "Attack": 1,
      "Defense": 1,
      "SpecialAttack": 1,
      "SpecialDefense": 1
    },
    {
      "RequiredExp": 20760,
      "HP": 1,
      "Attack": 1,
      "Defense": 0,
      "SpecialAttack": 1,
      "SpecialDefense": 0
    },
    {
      "RequiredExp": 25052,
      "HP": 1,
      "Attack": 1,
      "Defense": 1,
      "SpecialAttack": 1,
      "SpecialDefense": 1
    },
    {
      "RequiredExp": 29347,
      "HP": 1,
      "Attack": 1,
      "Defense": 0,
      "SpecialAttack": 1,
      "SpecialDefense": 0
    },
    {
      "RequiredExp": 33644,
      "HP": 1,
      "Attack": 1,
      "Defense": 1,
      "SpecialAttack": 1,
      "SpecialDefense": 1
    },
    {
      "RequiredExp": 37975,
      "HP": 1,
      "Attack": 1,
      "Defense": 0,
      "SpecialAttack": 1,
      "SpecialDefense": 0
    },
    {
      "RequiredExp": 42992,
      "HP": 1,
      "Attack": 1,
      "Defense": 1,
      "SpecialAttack": 1,
      "SpecialDefense": 1
    },
    {
      "RequiredExp": 48013,
      "HP": 1,
      "Attack": 1,
      "Defense": 0,
      "SpecialAttack": 1,
      "SpecialDefense": 0
    },
    {
      "RequiredExp": 53039,
      "HP": 1,
      "Attack": 1,
      "Defense": 1,
      "SpecialAttack": 1,
      "SpecialDefense": 1
    },
    {
      "RequiredExp": 59439,
      "HP": 2,
      "Attack": 2,
      "Defense": 2,
      "SpecialAttack": 2,
      "SpecialDefense": 2
    },
    {
      "RequiredExp": 67226,
      "HP": 2,
      "Attack": 2,
      "Defense": 2,
      "SpecialAttack": 2,
      "SpecialDefense": 2
    },
    {
      "RequiredExp": 75699,
      "HP": 3,
      "Attack": 2,
      "Defense": 2,
      "SpecialAttack": 2,
      "SpecialDefense": 2
    },
    {
      "RequiredExp": 84857,
      "HP": 3,
      "Attack": 2,
      "Defense": 2,
      "SpecialAttack": 2,
      "SpecialDefense": 2
    },
    {
      "RequiredExp": 94703,
      "HP": 3,
      "Attack": 2,
      "Defense": 2,
      "SpecialAttack": 2,
      "SpecialDefense": 2
    },
    {
      "RequiredExp": 105234,
      "HP": 3,
      "Attack": 2,
      "Defense": 2,
      "SpecialAttack": 2,
      "SpecialDefense": 2
    },
    {
      "RequiredExp": 116453,
      "HP": 3,
      "Attack": 2,
      "Defense": 2,
      "SpecialAttack": 2,
      "SpecialDefense": 2
    },
    {
      "RequiredExp": 128357,
      "HP": 3,
      "Attack": 2,
      "Defense": 2,
      "SpecialAttack": 2,
      "SpecialDefense": 2
    },
    {
      "RequiredExp": 142332,
      "HP": 3,
      "Attack": 2,
      "Defense": 2,
      "SpecialAttack": 2,
      "SpecialDefense": 2
    },
    {
      "RequiredExp": 156992,
      "HP": 3,
      "Attack": 1,
      "Defense": 1,
      "SpecialAttack": 1,
      "SpecialDefense": 1
    },
    {
      "RequiredExp": 172338,
      "HP": 3,
      "Attack": 1,
      "Defense": 2,
      "SpecialAttack": 1,
      "SpecialDefense": 2
    },
    {
      "RequiredExp": 188371,
      "HP": 2,
      "Attack": 1,
      "Defense": 1,
      "SpecialAttack": 1,
      "SpecialDefense": 1
    },
    {
      "RequiredExp": 205090,
      "HP": 2,
      "Attack": 1,
      "Defense": 2,
      "SpecialAttack": 1,
      "SpecialDefense": 2
    },
    {
      "RequiredExp": 222496,
      "HP": 2,
      "Attack": 1,
      "Defense": 1,
      "SpecialAttack": 1,
      "SpecialDefense": 1
    },
    {
      "RequiredExp": 240588,
      "HP": 2,
      "Attack": 1,
      "Defense": 1,
      "SpecialAttack": 1,
      "SpecialDefense": 1
    },
    {
      "RequiredExp": 259366,
      "HP": 1,
      "Attack": 1,
      "Defense": 1,
      "SpecialAttack": 1,
      "SpecialDefense": 1
    },
    {
      "RequiredExp": 278831,
      "HP": 1,
      "Attack": 1,
      "Defense": 1,
      "SpecialAttack": 1,
      "SpecialDefense": 1
    },
    {
      "RequiredExp": 298982,
      "HP": 1,
      "Attack": 1,
      "Defense": 1,
      "SpecialAttack": 1,
      "SpecialDefense": 1
    },
    {
      "RequiredExp": 319819,
      "HP": 1,
      "Attack": 1,
      "Defense": 1,
      "SpecialAttack": 1,
      "SpecialDefense": 1
    },
    {
      "RequiredExp": 342029,
      "HP": 1,
      "Attack": 1,
      "Defense": 1,
      "SpecialAttack": 1,
      "SpecialDefense": 1
    },
    {
      "RequiredExp": 365612,
      "HP": 1,
      "Attack": 1,
      "Defense": 1,
      "SpecialAttack": 1,
      "SpecialDefense": 1
    },
    {
      "RequiredExp": 390567,
      "HP": 1,
      "Attack": 1,
      "Defense": 1,
      "SpecialAttack": 1,
      "SpecialDefense": 1
    },
    {
      "RequiredExp": 416896,
      "HP": 1,
      "Attack": 1,
      "Defense": 1,
      "SpecialAttack": 1,
      "SpecialDefense": 1
    },
    {
      "RequiredExp": 444597,
      "HP": 1,
      "Attack": 1,
      "Defense": 1,
      "SpecialAttack": 1,
      "SpecialDefense": 1
    },
    {
      "RequiredExp": 473670,
      "HP": 1,
      "Attack": 1,
      "Defense": 1,
      "SpecialAttack": 1,
      "SpecialDefense": 1
    },
    {
      "RequiredExp": 504116,
      "HP": 1,
      "Attack": 1,
      "Defense": 1,
      "SpecialAttack": 1,
      "SpecialDefense": 1
    },
    {
      "RequiredExp": 535935,
      "HP": 1,
      "Attack": 1,
      "Defense": 1,
      "SpecialAttack": 1,
      "SpecialDefense": 1
    },
    {
      "RequiredExp": 569127,
      "HP": 1,
      "Attack": 1,
      "Defense": 1,
      "SpecialAttack": 1,
      "SpecialDefense": 1
    },
    {
      "RequiredExp": 603452,
      "HP": 1,
      "Attack": 1,
      "Defense": 1,
      "SpecialAttack": 1,
      "SpecialDefense": 1
    },
    {
      "RequiredExp": 637783,
      "HP": 1,
      "Attack": 1,
      "Defense": 1,
      "SpecialAttack": 1,
      "SpecialDefense": 1
    },
    {
      "RequiredExp": 672121,
      "HP": 1,
      "Attack": 1,
      "Defense": 1,
      "SpecialAttack": 1,
      "SpecialDefense": 1
    },
    {
      "RequiredExp": 706466,
      "HP": 1,
      "Attack": 1,
      "Defense": 1,
      "SpecialAttack": 1,
      "SpecialDefense": 1
    },
    {
      "RequiredExp": 740818,
      "HP": 1,
      "Attack": 1,
      "Defense": 1,
      "SpecialAttack": 1,
      "SpecialDefense": 1
    },
    {
      "RequiredExp": 775177,
      "HP": 1,
      "Attack": 1,
      "Defense": 1,
      "SpecialAttack": 1,
      "SpecialDefense": 1
    },
    {
      "RequiredExp": 809542,
      "HP": 1,
      "Attack": 1,
      "Defense": 1,
      "SpecialAttack": 1,
      "SpecialDefense": 1
    },
    {
      "RequiredExp": 843915,
      "HP": 1,
      "Attack": 1,
      "Defense": 1,
      "SpecialAttack": 1,
      "SpecialDefense": 1
    },
    {
      "RequiredExp": 878294,
      "HP": 1,
      "Attack": 1,
      "Defense": 1,
      "SpecialAttack": 1,
      "SpecialDefense": 1
    },
    {
      "RequiredExp": 912680,
      "HP": 1,
      "Attack": 1,
      "Defense": 1,
      "SpecialAttack": 1,
      "SpecialDefense": 1
    },
    {
      "RequiredExp": 947073,
      "HP": 1,
      "Attack": 1,
      "Defense": 1,
      "SpecialAttack": 1,
      "SpecialDefense": 1
    },
    {
      "RequiredExp": 981473,
      "HP": 1,
      "Attack": 1,
      "Defense": 1,
      "SpecialAttack": 1,
      "SpecialDefense": 1
    },
    {
      "RequiredExp": 1015879,
      "HP": 1,
      "Attack": 1,
      "Defense": 1,
      "SpecialAttack": 1,
      "SpecialDefense": 1
    },
    {
      "RequiredExp": 1050293,
      "HP": 1,
      "Attack": 1,
      "Defense": 1,
      "SpecialAttack": 1,
      "SpecialDefense": 1
    },
    {
      "RequiredExp": 1084714,
      "HP": 1,
      "Attack": 1,
      "Defense": 1,
      "SpecialAttack": 1,
      "SpecialDefense": 1
    },
    {
      "RequiredExp": 1119141,
      "HP": 1,
      "Attack": 1,
      "Defense": 1,
      "SpecialAttack": 1,
      "SpecialDefense": 1
    },
    {
      "RequiredExp": 1153575,
      "HP": 1,
      "Attack": 1,
      "Defense": 1,
      "SpecialAttack": 1,
      "SpecialDefense": 1
    },
    {
      "RequiredExp": 1188016,
      "HP": 1,
      "Attack": 1,
      "Defense": 1,
      "SpecialAttack": 1,
      "SpecialDefense": 1
    },
    {
      "RequiredExp": 1222464,
      "HP": 1,
      "Attack": 1,
      "Defense": 1,
      "SpecialAttack": 1,
      "SpecialDefense": 1
    },
    {
      "RequiredExp": 1256919,
      "HP": 1,
      "Attack": 1,
      "Defense": 1,
      "SpecialAttack": 1,
      "SpecialDefense": 1
    },
    {
      "RequiredExp": 1291380,
      "HP": 1,
      "Attack": 1,
      "Defense": 1,
      "SpecialAttack": 1,
      "SpecialDefense": 1
    },
    {
      "RequiredExp": 1325849,
      "HP": 1,
      "Attack": 1,
      "Defense": 1,
      "SpecialAttack": 1,
      "SpecialDefense": 1
    },
    {
      "RequiredExp": 1360324,
      "HP": 1,
      "Attack": 1,
      "Defense": 1,
      "SpecialAttack": 1,
      "SpecialDefense": 1
    },
    {
      "RequiredExp": 1394806,
      "HP": 1,
      "Attack": 1,
      "Defense": 1,
      "SpecialAttack": 1,
      "SpecialDefense": 1
    },
    {
      "RequiredExp": 1429296,
      "HP": 1,
      "Attack": 1,
      "Defense": 1,
      "SpecialAttack": 1,
      "SpecialDefense": 1
    },
    {
      "RequiredExp": 1463792,
      "HP": 1,
      "Attack": 1,
      "Defense": 1,
      "SpecialAttack": 1,
      "SpecialDefense": 1
    },
    {
      "RequiredExp": 1498294,
      "HP": 1,
      "Attack": 1,
      "Defense": 1,
      "SpecialAttack": 1,
      "SpecialDefense": 1
    },
    {
      "RequiredExp": 1532804,
      "HP": 1,
      "Attack": 1,
      "Defense": 1,
      "SpecialAttack": 1,
      "SpecialDefense": 1
    },
    {
      "RequiredExp": 1567321,
      "HP": 1,
      "Attack": 1,
      "Defense": 1,
      "SpecialAttack": 1,
      "SpecialDefense": 1
    },
    {
      "RequiredExp": 1601844,
      "HP": 1,
      "Attack": 1,
      "Defense": 1,
      "SpecialAttack": 1,
      "SpecialDefense": 1
    },
    {
      "RequiredExp": 1636374,
      "HP": 1,
      "Attack": 1,
      "Defense": 1,
      "SpecialAttack": 1,
      "SpecialDefense": 1
    },
    {
      "RequiredExp": 1670911,
      "HP": 1,
      "Attack": 1,
      "Defense": 1,
      "SpecialAttack": 1,
      "SpecialDefense": 1
    },
    {
      "RequiredExp": 1705456,
      "HP": 1,
      "Attack": 1,
      "Defense": 1,
      "SpecialAttack": 1,
      "SpecialDefense": 1
    },
    {
      "RequiredExp": 1740006,
      "HP": 1,
      "Attack": 1,
      "Defense": 1,
      "SpecialAttack": 1,
      "SpecialDefense": 1
    },
    {
      "RequiredExp": 1774564,
      "HP": 1,
      "Attack": 1,
      "Defense": 1,
      "SpecialAttack": 1,
      "SpecialDefense": 1
    },
    {
      "RequiredExp": 1809129,
      "HP": 1,
      "Attack": 1,
      "Defense": 1,
      "SpecialAttack": 1,
      "SpecialDefense": 1
    },
    {
      "RequiredExp": 1843700,
      "HP": 1,
      "Attack": 1,
      "Defense": 1,
      "SpecialAttack": 1,
      "SpecialDefense": 1
    },
    {
      "RequiredExp": 1878278,
      "HP": 1,
      "Attack": 1,
      "Defense": 1,
      "SpecialAttack": 1,
      "SpecialDefense": 1
    },
    {
      "RequiredExp": 1912864,
      "HP": 1,
      "Attack": 1,
      "Defense": 1,
      "SpecialAttack": 1,
      "SpecialDefense": 1
    },
    {
      "RequiredExp": 1947456,
      "HP": 1,
      "Attack": 1,
      "Defense": 1,
      "SpecialAttack": 1,
      "SpecialDefense": 1
    },
    {
      "RequiredExp": 1982055,
      "HP": 1,
      "Attack": 1,
      "Defense": 1,
      "SpecialAttack": 1,
      "SpecialDefense": 1
    },
    {
      "RequiredExp": 2016661,
      "HP": 1,
      "Attack": 1,
      "Defense": 1,
      "SpecialAttack": 1,
      "SpecialDefense": 1
    },
    {
      "RequiredExp": 2051273,
      "HP": 1,
      "Attack": 1,
      "Defense": 1,
      "SpecialAttack": 1,
      "SpecialDefense": 1
    },
    {
      "RequiredExp": 2085893,
      "HP": 1,
      "Attack": 1,
      "Defense": 1,
      "SpecialAttack": 1,
      "SpecialDefense": 1
    },
    {
      "RequiredExp": 2120519,
      "HP": 1,
      "Attack": 1,
      "Defense": 1,
      "SpecialAttack": 1,
      "SpecialDefense": 1
    },
    {
      "RequiredExp": 2155152,
      "HP": 1,
      "Attack": 1,
      "Defense": 1,
      "SpecialAttack": 1,
      "SpecialDefense": 1
    },
    {
      "RequiredExp": 2189793,
      "HP": 1,
      "Attack": 1,
      "Defense": 1,
      "SpecialAttack": 1,
      "SpecialDefense": 1
    },
    {
      "RequiredExp": 2224480,
      "HP": 1,
      "Attack": 1,
      "Defense": 1,
      "SpecialAttack": 1,
      "SpecialDefense": 1
    }
  ],
  "GenderEnitities": [
    {
      "Evolution": {
        "PreEvoDexId": 399,
        "PreEvoRawId": 434,
        "Method": 1,
        "Param1": 15,
        "Param2": null
      },
      "Gender": 1,
      "IQGroup": 5,
      "PrimaryAbility": 97,
      "SecondaryAbility": 103,
      "BaseExpYield": 95,
      "RecruitRate": 35.0,
      "BaseStats": {
        "HP": 40,
        "Attack": 9,
        "Defense": 9,
        "SpecialAttack": 9,
        "SpecialDefense": 9
      },
      "ExclusiveItems": {
        "OneStarExclusiveA": 894,
        "OneStarExclusiveB": 895,
        "TwoStarExclusive": 896,
        "ThreeStarExclusive": 897
      }
    },
    {
      "Evolution": {
        "PreEvoDexId": 399,
        "PreEvoRawId": 1034,
        "Method": 1,
        "Param1": 15,
        "Param2": null
      },
      "Gender": 2,
      "IQGroup": 5,
      "PrimaryAbility": 97,
      "SecondaryAbility": 103,
      "BaseExpYield": 95,
      "RecruitRate": 35.0,
      "BaseStats": {
        "HP": 40,
        "Attack": 9,
        "Defense": 9,
        "SpecialAttack": 9,
        "SpecialDefense": 9
      },
      "ExclusiveItems": {
        "OneStarExclusiveA": 894,
        "OneStarExclusiveB": 895,
        "TwoStarExclusive": 896,
        "ThreeStarExclusive": 897
      }
    }
  ],
  "Movesets": [
    {
      "LevelUpMoves": [
        {
          "Level": 1,
          "MoveId": 154
        },
        {
          "Level": 1,
          "MoveId": 217
        },
        {
          "Level": 5,
          "MoveId": 217
        },
        {
          "Level": 9,
          "MoveId": 302
        },
        {
          "Level": 13,
          "MoveId": 105
        },
        {
          "Level": 15,
          "MoveId": 308
        },
        {
          "Level": 18,
          "MoveId": 139
        },
        {
          "Level": 23,
          "MoveId": 261
        },
        {
          "Level": 28,
          "MoveId": 3
        },
        {
          "Level": 33,
          "MoveId": 215
        },
        {
          "Level": 38,
          "MoveId": 203
        },
        {
          "Level": 43,
          "MoveId": 20
        },
        {
          "Level": 48,
          "MoveId": 243
        },
        {
          "Level": 53,
          "MoveId": 237
        }
      ],
      "EggMoves": null,
      "HmTmMoves": {
        "MoveIds": [
          1,
          8,
          12,
          18,
          24,
          29,
          48,
          50,
          56,
          64,
          67,
          75,
          104,
          127,
          129,
          158,
          172,
          189,
          192,
          197,
          214,
          219,
          223,
          227,
          232,
          242,
          263,
          270,
          301,
          304,
          310,
          324,
          326,
          328,
          345,
          360,
          394,
          455,
          458,
          471,
          480,
          489,
          490,
          503,
          534,
          541
        ]
      }
    },
    {
      "LevelUpMoves": [
        {
          "Level": 1,
          "MoveId": 154
        },
        {
          "Level": 1,
          "MoveId": 217
        },
        {
          "Level": 5,
          "MoveId": 217
        },
        {
          "Level": 9,
          "MoveId": 302
        },
        {
          "Level": 13,
          "MoveId": 105
        },
        {
          "Level": 15,
          "MoveId": 308
        },
        {
          "Level": 18,
          "MoveId": 139
        },
        {
          "Level": 23,
          "MoveId": 261
        },
        {
          "Level": 28,
          "MoveId": 3
        },
        {
          "Level": 33,
          "MoveId": 215
        },
        {
          "Level": 38,
          "MoveId": 203
        },
        {
          "Level": 43,
          "MoveId": 20
        },
        {
          "Level": 48,
          "MoveId": 243
        }
      ],
      "EggMoves": null,
      "HmTmMoves": {
        "MoveIds": [
          1,
          8,
          12,
          18,
          24,
          29,
          48,
          50,
          56,
          64,
          67,
          75,
          104,
          127,
          129,
          158,
          172,
          189,
          192,
          197,
          214,
          219,
          223,
          227,
          232,
          242,
          263,
          270,
          301,
          304,
          310,
          324,
          326,
          328,
          345,
          360,
          394,
          455,
          458,
          471,
          480,
          489,
          490,
          503,
          534,
          541
        ]
      }
    }
  ]
}