{
  "Id": "cleffa",
  "DexId": 173,
  "RawIndex": 173,
  "Name": "Cleffa",
  "GameSeries": 1,
  "PrimaryType": 1,
  "SecondaryType": 0,
  "Category": "Star Shape",
  "LevelStats": [
    {
      "RequiredExp": 0,
      "HP": 0,
      "Attack": 0,
      "Defense": 0,
      "SpecialAttack": 0,
      "SpecialDefense": 0
    },
    {
      "RequiredExp": 8,
      "HP": 1,
      "Attack": 0,
      "Defense": 1,
      "SpecialAttack": 0,
      "SpecialDefense": 0
    },
    {
      "RequiredExp": 20,
      "HP": 0,
      "Attack": 1,
      "Defense": 0,
      "SpecialAttack": 0,
      "SpecialDefense": 1
    },
    {
      "RequiredExp": 36,
      "HP": 1,
      "Attack": 0,
      "Defense": 0,
      "SpecialAttack": 1,
      "SpecialDefense": 0
    },
    {
      "RequiredExp": 78,
      "HP": 0,
      "Attack": 1,
      "Defense": 1,
      "SpecialAttack": 0,
      "SpecialDefense": 0
    },
    {
      "RequiredExp": 171,
      "HP": 1,
      "Attack": 0,
      "Defense": 0,
      "SpecialAttack": 0,
      "SpecialDefense": 1
    },
    {
      "RequiredExp": 266,
      "HP": 0,
      "Attack": 1,
      "Defense": 0,
      "SpecialAttack": 1,
      "SpecialDefense": 0
    },
    {
      "RequiredExp": 499,
      "HP": 1,
      "Attack": 0,
      "Defense": 1,
      "SpecialAttack": 0,
      "SpecialDefense": 0
    },
    {
      "RequiredExp": 1007,
      "HP": 0,
      "Attack": 1,
      "Defense": 0,
      "SpecialAttack": 0,
      "SpecialDefense": 1
    },
    {
      "RequiredExp": 1518,
      "HP": 1,
      "Attack": 0,
      "Defense": 0,
      "SpecialAttack": 1,
      "SpecialDefense": 0
    },
    {
      "RequiredExp": 2321,
      "HP": 0,
      "Attack": 1,
      "Defense": 1,
      "SpecialAttack": 0,
      "SpecialDefense": 0
    },
    {
      "RequiredExp": 4284,
      "HP": 1,
      "Attack": 0,
      "Defense": 0,
      "SpecialAttack": 0,
      "SpecialDefense": 1
    },
    {
      "RequiredExp": 6251,
      "HP": 0,
      "Attack": 1,
      "Defense": 0,
      "SpecialAttack": 1,
      "SpecialDefense": 0
    },
    {
      "RequiredExp": 9746,
      "HP": 1,
      "Attack": 0,
      "Defense": 1,
      "SpecialAttack": 0,
      "SpecialDefense": 0
    },
    {
      "RequiredExp": 13243,
      "HP": 0,
      "Attack": 1,
      "Defense": 0,
      "SpecialAttack": 0,
      "SpecialDefense": 1
    },
    {
      "RequiredExp": 17165,
      "HP": 5,
      "Attack": 3,
      "Defense": 3,
      "SpecialAttack": 3,
      "SpecialDefense": 3
    },
    {
      "RequiredExp": 21092,
      "HP": 5,
      "Attack": 3,
      "Defense": 3,
      "SpecialAttack": 3,
      "SpecialDefense": 3
    },
    {
      "RequiredExp": 25452,
      "HP": 5,
      "Attack": 3,
      "Defense": 3,
      "SpecialAttack": 3,
      "SpecialDefense": 3
    },
    {
      "RequiredExp": 29816,
      "HP": 4,
      "Attack": 3,
      "Defense": 3,
      "SpecialAttack": 3,
      "SpecialDefense": 3
    },
    {
      "RequiredExp": 34183,
      "HP": 4,
      "Attack": 2,
      "Defense": 3,
      "SpecialAttack": 3,
      "SpecialDefense": 3
    },
    {
      "RequiredExp": 38582,
      "HP": 4,
      "Attack": 2,
      "Defense": 3,
      "SpecialAttack": 3,
      "SpecialDefense": 2
    },
    {
      "RequiredExp": 43679,
      "HP": 4,
      "Attack": 2,
      "Defense": 3,
      "SpecialAttack": 3,
      "SpecialDefense": 2
    },
    {
      "RequiredExp": 48781,
      "HP": 4,
      "Attack": 2,
      "Defense": 2,
      "SpecialAttack": 3,
      "SpecialDefense": 2
    },
    {
      "RequiredExp": 53888,
      "HP": 4,
      "Attack": 2,
      "Defense": 1,
      "SpecialAttack": 3,
      "SpecialDefense": 2
    },
    {
      "RequiredExp": 60390,
      "HP": 4,
      "Attack": 2,
      "Defense": 1,
      "SpecialAttack": 3,
      "SpecialDefense": 2
    },
    {
      "RequiredExp": 68301,
      "HP": 4,
      "Attack": 2,
      "Defense": 1,
      "SpecialAttack": 2,
      "SpecialDefense": 1
    },
    {
      "RequiredExp": 76909,
      "HP": 4,
      "Attack": 2,
      "Defense": 1,
      "SpecialAttack": 2,
      "SpecialDefense": 1
    },
    {
      "RequiredExp": 86215,
      "HP": 3,
      "Attack": 1,
      "Defense": 0,
      "SpecialAttack": 2,
      "SpecialDefense": 1
    },
    {
      "RequiredExp": 96218,
      "HP": 3,
      "Attack": 1,
      "Defense": 1,
      "SpecialAttack": 1,
      "SpecialDefense": 1
    },
    {
      "RequiredExp": 106918,
      "HP": 3,
      "Attack": 0,
      "Defense": 0,
      "SpecialAttack": 1,
      "SpecialDefense": 1
    },
    {
      "RequiredExp": 118316,
      "HP": 3,
      "Attack": 1,
      "Defense": 0,
      "SpecialAttack": 1,
      "SpecialDefense": 1
    },
    {
      "RequiredExp": 130411,
      "HP": 3,
      "Attack": 0,
      "Defense": 1,
      "SpecialAttack": 0,
      "SpecialDefense": 0
    },
    {
      "RequiredExp": 144608,
      "HP": 3,
      "Attack": 1,
      "Defense": 0,
      "SpecialAttack": 0,
      "SpecialDefense": 1
    },
    {
      "RequiredExp": 159503,
      "HP": 3,
      "Attack": 0,
      "Defense": 0,
      "SpecialAttack": 1,
      "SpecialDefense": 0
    },
    {
      "RequiredExp": 175095,
      "HP": 3,
      "Attack": 1,
      "Defense": 1,
      "SpecialAttack": 0,
      "SpecialDefense": 0
    },
    {
      "RequiredExp": 191384,
      "HP": 1,
      "Attack": 0,
      "Defense": 0,
      "SpecialAttack": 0,
      "SpecialDefense": 1
    },
    {
      "RequiredExp": 208371,
      "HP": 0,
      "Attack": 1,
      "Defense": 0,
      "SpecialAttack": 1,
      "SpecialDefense": 0
    },
    {
      "RequiredExp": 226055,
      "HP": 1,
      "Attack": 0,
      "Defense": 1,
      "SpecialAttack": 0,
      "SpecialDefense": 0
    },
    {
      "RequiredExp": 244436,
      "HP": 0,
      "Attack": 1,
      "Defense": 0,
      "SpecialAttack": 0,
      "SpecialDefense": 1
    },
    {
      "RequiredExp": 263515,
      "HP": 1,
      "Attack": 0,
      "Defense": 0,
      "SpecialAttack": 1,
      "SpecialDefense": 0
    },
    {
      "RequiredExp": 283291,
      "HP": 0,
      "Attack": 1,
      "Defense": 1,
      "SpecialAttack": 0,
      "SpecialDefense": 0
    },
    {
      "RequiredExp": 303765,
      "HP": 1,
      "Attack": 0,
      "Defense": 0,
      "SpecialAttack": 0,
      "SpecialDefense": 1
    },
    {
      "RequiredExp": 324935,
      "HP": 0,
      "Attack": 1,
      "Defense": 0,
      "SpecialAttack": 1,
      "SpecialDefense": 0
    },
    {
      "RequiredExp": 347501,
      "HP": 1,
      "Attack": 0,
      "Defense": 1,
      "SpecialAttack": 0,
      "SpecialDefense": 0
    },
    {
      "RequiredExp": 371461,
      "HP": 0,
      "Attack": 1,
      "Defense": 0,
      "SpecialAttack": 0,
      "SpecialDefense": 1
    },
    {
      "RequiredExp": 396815,
      "HP": 1,
      "Attack": 0,
      "Defense": 0,
      "SpecialAttack": 1,
      "SpecialDefense": 0
    },
    {
      "RequiredExp": 423564,
      "HP": 0,
      "Attack": 1,
      "Defense": 1,
      "SpecialAttack": 0,
      "SpecialDefense": 0
    },
    {
      "RequiredExp": 451709,
      "HP": 1,
      "Attack": 0,
      "Defense": 0,
      "SpecialAttack": 0,
      "SpecialDefense": 1
    },
    {
      "RequiredExp": 481248,
      "HP": 0,
      "Attack": 1,
      "Defense": 0,
      "SpecialAttack": 1,
      "SpecialDefense": 0
    },
    {
      "RequiredExp": 512181,
      "HP": 1,
      "Attack": 0,
      "Defense": 1,
      "SpecialAttack": 0,
      "SpecialDefense": 0
    },
    {
      "RequiredExp": 544509,
      "HP": 0,
      "Attack": 1,
      "Defense": 0,
      "SpecialAttack": 0,
      "SpecialDefense": 1
    },
    {
      "RequiredExp": 578231,
      "HP": 1,
      "Attack": 0,
      "Defense": 0,
      "SpecialAttack": 1,
      "SpecialDefense": 0
    },
    {
      "RequiredExp": 613105,
      "HP": 0,
      "Attack": 1,
      "Defense": 1,
      "SpecialAttack": 0,
      "SpecialDefense": 0
    },
    {
      "RequiredExp": 647985,
      "HP": 1,
      "Attack": 0,
      "Defense": 0,
      "SpecialAttack": 0,
      "SpecialDefense": 1
    },
    {
      "RequiredExp": 682872,
      "HP": 0,
      "Attack": 1,
      "Defense": 0,
      "SpecialAttack": 1,
      "SpecialDefense": 0
    },
    {
      "RequiredExp": 717767,
      "HP": 1,
      "Attack": 0,
      "Defense": 1,
      "SpecialAttack": 0,
      "SpecialDefense": 0
    },
    {
      "RequiredExp": 752669,
      "HP": 0,
      "Attack": 1,
      "Defense": 0,
      "SpecialAttack": 0,
      "SpecialDefense": 1
    },
    {
      "RequiredExp": 787577,
      "HP": 1,
      "Attack": 0,
      "Defense": 0,
      "SpecialAttack": 1,
      "SpecialDefense": 0
    },
    {
      "RequiredExp": 822492,
      "HP": 0,
      "Attack": 1,
      "Defense": 1,
      "SpecialAttack": 0,
      "SpecialDefense": 0
    },
    {
      "RequiredExp": 857414,
      "HP": 1,
      "Attack": 1,
      "Defense": 1,
      "SpecialAttack": 1,
      "SpecialDefense": 1
    },
    {
      "RequiredExp": 892343,
      "HP": 1,
      "Attack": 1,
      "Defense": 1,
      "SpecialAttack": 1,
      "SpecialDefense": 1
    },
    {
      "RequiredExp": 927279,
      "HP": 1,
      "Attack": 1,
      "Defense": 1,
      "SpecialAttack": 1,
      "SpecialDefense": 1
    },
    {
      "RequiredExp": 962223,
      "HP": 1,
      "Attack": 1,
      "Defense": 1,
      "SpecialAttack": 1,
      "SpecialDefense": 1
    },
    {
      "RequiredExp": 997173,
      "HP": 1,
      "Attack": 1,
      "Defense": 1,
      "SpecialAttack": 1,
      "SpecialDefense": 1
    },
    {
      "RequiredExp": 1032130,
      "HP": 1,
      "Attack": 1,
      "Defense": 1,
      "SpecialAttack": 1,
      "SpecialDefense": 1
    },
    {
      "RequiredExp": 1067094,
      "HP": 1,
      "Attack": 1,
      "Defense": 1,
      "SpecialAttack": 1,
      "SpecialDefense": 1
    },
    {
      "RequiredExp": 1102065,
      "HP": 1,
      "Attack": 1,
      "Defense": 1,
      "SpecialAttack": 1,
      "SpecialDefense": 1
    },
    {
      "RequiredExp": 1137043,
      "HP": 1,
      "Attack": 1,
      "Defense": 1,
      "SpecialAttack": 1,
      "SpecialDefense": 1
    },
    {
      "RequiredExp": 1172028,
      "HP": 1,
      "Attack": 1,
      "Defense": 1,
      "SpecialAttack": 1,
      "SpecialDefense": 1
    },
    {
      "RequiredExp": 1207020,
      "HP": 1,
      "Attack": 1,
      "Defense": 1,
      "SpecialAttack": 1,
      "SpecialDefense": 1
    },
    {
      "RequiredExp": 1242019,
      "HP": 1,
      "Attack": 1,
      "Defense": 1,
      "SpecialAttack": 1,
      "SpecialDefense": 1
    },
    {
      "RequiredExp": 1277025,
      "HP": 1,
      "Attack": 1,
      "Defense": 1,
      "SpecialAttack": 1,
      "SpecialDefense": 1
    },
    {
      "RequiredExp": 1312038,
      "HP": 1,
      "Attack": 1,
      "Defense": 1,
      "SpecialAttack": 1,
      "SpecialDefense": 1
    },
    {
      "RequiredExp": 1347058,
      "HP": 1,
      "Attack": 1,
      "Defense": 1,
      "SpecialAttack": 1,
      "SpecialDefense": 1
    },
    {
      "RequiredExp": 1382085,
      "HP": 1,
      "Attack": 1,
      "Defense": 1,
      "SpecialAttack": 1,
      "SpecialDefense": 1
    },
    {
      "RequiredExp": 1417118,
      "HP": 1,
      "Attack": 1,
      "Defense": 1,
      "SpecialAttack": 1,
      "SpecialDefense": 1
    },
    {
      "RequiredExp": 1452159,
      "HP": 1,
      "Attack": 1,
      "Defense": 1,
      "SpecialAttack": 1,
      "SpecialDefense": 1
    },
    {
      "RequiredExp": 1487207,
      "HP": 1,
      "Attack": 1,
      "Defense": 1,
      "SpecialAttack": 1,
      "SpecialDefense": 1
    },
    {
      "RequiredExp": 1522262,
      "HP": 1,
      "Attack": 1,
      "Defense": 1,
      "SpecialAttack": 1,
      "SpecialDefense": 1
    },
    {
      "RequiredExp": 1557324,
      "HP": 1,
      "Attack": 1,
      "Defense": 1,
      "SpecialAttack": 1,
      "SpecialDefense": 1
    },
    {
      "RequiredExp": 1592393,
      "HP": 1,
      "Attack": 1,
      "Defense": 1,
      "SpecialAttack": 1,
      "SpecialDefense": 1
    },
    {
      "RequiredExp": 1627468,
      "HP": 1,
      "Attack": 1,
      "Defense": 1,
      "SpecialAttack": 1,
      "SpecialDefense": 1
    },
    {
      "RequiredExp": 1662550,
      "HP": 1,
      "Attack": 1,
      "Defense": 1,
      "SpecialAttack": 1,
      "SpecialDefense": 1
    },
    {
      "RequiredExp": 1697640,
      "HP": 1,
      "Attack": 1,
      "Defense": 1,
      "SpecialAttack": 1,
      "SpecialDefense": 1
    },
    {
      "RequiredExp": 1732737,
      "HP": 1,
      "Attack": 1,
      "Defense": 1,
      "SpecialAttack": 1,
      "SpecialDefense": 1
    },
    {
      "RequiredExp": 1767841,
      "HP": 1,
      "Attack": 1,
      "Defense": 1,
      "SpecialAttack": 1,
      "SpecialDefense": 1
    },
    {
      "RequiredExp": 1802951,
      "HP": 1,
      "Attack": 1,
      "Defense": 1,
      "SpecialAttack": 1,
      "SpecialDefense": 1
    },
    {
      "RequiredExp": 1838069,
      "HP": 1,
      "Attack": 1,
      "Defense": 1,
      "SpecialAttack": 1,
      "SpecialDefense": 1
    },
    {
      "RequiredExp": 1873193,
      "HP": 1,
      "Attack": 1,
      "Defense": 1,
      "SpecialAttack": 1,
      "SpecialDefense": 1
    },
    {
      "RequiredExp": 1908324,
      "HP": 1,
      "Attack": 1,
      "Defense": 1,
      "SpecialAttack": 1,
      "SpecialDefense": 1
    },
    {
      "RequiredExp": 1943463,
      "HP": 1,
      "Attack": 1,
      "Defense": 1,
      "SpecialAttack": 1,
      "SpecialDefense": 1
    },
    {
      "RequiredExp": 1978609,
      "HP": 1,
      "Attack": 1,
      "Defense": 1,
      "SpecialAttack": 1,
      "SpecialDefense": 1
    },
    {
      "RequiredExp": 2013761,
      "HP": 1,
      "Attack": 1,
      "Defense": 1,
      "SpecialAttack": 1,
      "SpecialDefense": 1
    },
    {
      "RequiredExp": 2048920,
      "HP": 1,
      "Attack": 1,
      "Defense": 1,
      "SpecialAttack": 1,
      "SpecialDefense": 1
    },
    {
      "RequiredExp": 2084087,
      "HP": 1,
      "Attack": 1,
      "Defense": 1,
      "SpecialAttack": 1,
      "SpecialDefense": 1
    },
    {
      "RequiredExp": 2119260,
      "HP": 1,
      "Attack": 1,
      "Defense": 1,
      "SpecialAttack": 1,
      "SpecialDefense": 1
    },
    {
      "RequiredExp": 2154440,
      "HP": 1,
      "Attack": 1,
      "Defense": 1,
      "SpecialAttack": 1,
      "SpecialDefense": 1
    },
    {
      "RequiredExp": 2189627,
      "HP": 1,
      "Attack": 1,
      "Defense": 1,
      "SpecialAttack": 1,
      "SpecialDefense": 1
    },
    {
      "RequiredExp": 2224822,
      "HP": 1,
      "Attack": 1,
      "Defense": 1,
      "SpecialAttack": 1,
      "SpecialDefense": 1
    },
    {
      "RequiredExp": 2260064,
      "HP": 1,
      "Attack": 1,
      "Defense": 1,
      "SpecialAttack": 1,
      "SpecialDefense": 1
    }
  ],
  "GenderEnitities": [
    {
      "Evolution": {
        "PreEvoDexId": 0,
        "PreEvoRawId": 0,
        "Method": 0,
        "Param1": null,
        "Param2": null
      },
      "Gender": 1,
      "IQGroup": 1,
      "PrimaryAbility": 68,
      "SecondaryAbility": 115,
      "BaseExpYield": 20,
      "RecruitRate": 8.2,
      "BaseStats": {
        "HP": 11,
        "Attack": 3,
        "Defense": 2,
        "SpecialAttack": 2,
        "SpecialDefense": 2
      },
      "ExclusiveItems": {
        "OneStarExclusiveA": 770,
        "OneStarExclusiveB": 771,
        "TwoStarExclusive": 772,
        "ThreeStarExclusive": 773
      }
    },
    {
      "Evolution": {
        "PreEvoDexId": 0,
        "PreEvoRawId": 0,
        "Method": 0,
        "Param1": null,
        "Param2": null
      },
      "Gender": 2,
      "IQGroup": 1,
      "PrimaryAbility": 68,
      "SecondaryAbility": 115,
      "BaseExpYield": 20,
      "RecruitRate": 8.2,
      "BaseStats": {
        "HP": 11,
        "Attack": 3,
        "Defense": 2,
        "SpecialAttack": 2,
        "SpecialDefense": 2
      },
      "ExclusiveItems": {
        "OneStarExclusiveA": 770,
        "OneStarExclusiveB": 771,
        "TwoStarExclusive": 772,
        "ThreeStarExclusive": 773
      }
    }
  ],
  "Movesets": [
    {
      "LevelUpMoves": [
        {
          "Level": 1,
          "MoveId": 11
        },
        {
          "Level": 1,
          "MoveId": 250
        },
        {
          "Level": 4,
          "MoveId": 17
        },
        {
          "Level": 7,
          "MoveId": 34
        },
        {
          "Level": 10,
          "MoveId": 191
        },
        {
          "Level": 13,
          "MoveId": 525
        },
        {
          "Level": 16,
          "MoveId": 297
        }
      ],
      "EggMoves": {
        "MoveIds": [
          33,
          215,
          225,
          254,
          257,
          277,
          287,
          304,
          327,
          330
        ]
      },
      "HmTmMoves": {
        "MoveIds": [
          1,
          8,
          12,
          24,
          48,
          53,
          56,
          67,
          104,
          109,
          115,
          127,
          134,
          151,
          157,
          189,
          192,
          197,
          223,
          227,
          232,
          259,
          263,
          273,
          301,
          304,
          310,
          324,
          326,
          328,
          331,
          337,
          338,
          360,
          394,
          458,
          471,
          503,
          534
        ]
      }
    },
    {
      "LevelUpMoves": [
        {
          "Level": 1,
          "MoveId": 11
        },
        {
          "Level": 1,
          "MoveId": 250
        },
        {
          "Level": 4,
          "MoveId": 17
        },
        {
          "Level": 7,
          "MoveId": 34
        },
        {
          "Level": 10,
          "MoveId": 191
        },
        {
          "Level": 13,
          "MoveId": 525
        },
        {
          "Level": 16,
          "MoveId": 297
        }
      ],
      "EggMoves": {
        "MoveIds": [
          33,
          215,
          225,
          254,
          257,
          277,
          287,
          304,
          327,
          330
        ]
      },
      "HmTmMoves": {
        "MoveIds": [
          1,
          8,
          12,
          24,
          48,
          53,
          56,
          67,
          104,
          109,
          115,
          127,
          134,
          151,
          157,
          189,
          192,
          197,
          223,
          227,
          232,
          259,
          263,
          273,
          301,
          304,
          310,
          324,
          326,
          328,
          331,
          337,
          338,
          360,
          394,
          458,
          471,
          503,
          534
        ]
      }
    }
  ]
}