{
  "Id": "scizor",
  "DexId": 212,
  "RawIndex": 239,
  "Name": "Scizor",
  "GameSeries": 1,
  "PrimaryType": 12,
  "SecondaryType": 17,
  "Category": "Pincer",
  "LevelStats": [
    {
      "RequiredExp": 0,
      "HP": 0,
      "Attack": 0,
      "Defense": 0,
      "SpecialAttack": 0,
      "SpecialDefense": 0
    },
    {
      "RequiredExp": 6,
      "HP": 1,
      "Attack": 1,
      "Defense": 1,
      "SpecialAttack": 1,
      "SpecialDefense": 1
    },
    {
      "RequiredExp": 17,
      "HP": 1,
      "Attack": 1,
      "Defense": 0,
      "SpecialAttack": 1,
      "SpecialDefense": 0
    },
    {
      "RequiredExp": 30,
      "HP": 1,
      "Attack": 1,
      "Defense": 1,
      "SpecialAttack": 1,
      "SpecialDefense": 1
    },
    {
      "RequiredExp": 65,
      "HP": 1,
      "Attack": 1,
      "Defense": 0,
      "SpecialAttack": 1,
      "SpecialDefense": 0
    },
    {
      "RequiredExp": 143,
      "HP": 1,
      "Attack": 1,
      "Defense": 1,
      "SpecialAttack": 1,
      "SpecialDefense": 1
    },
    {
      "RequiredExp": 222,
      "HP": 1,
      "Attack": 1,
      "Defense": 0,
      "SpecialAttack": 1,
      "SpecialDefense": 0
    },
    {
      "RequiredExp": 417,
      "HP": 1,
      "Attack": 1,
      "Defense": 1,
      "SpecialAttack": 1,
      "SpecialDefense": 1
    },
    {
      "RequiredExp": 841,
      "HP": 1,
      "Attack": 1,
      "Defense": 0,
      "SpecialAttack": 1,
      "SpecialDefense": 0
    },
    {
      "RequiredExp": 1267,
      "HP": 1,
      "Attack": 1,
      "Defense": 1,
      "SpecialAttack": 1,
      "SpecialDefense": 1
    },
    {
      "RequiredExp": 1937,
      "HP": 1,
      "Attack": 1,
      "Defense": 0,
      "SpecialAttack": 1,
      "SpecialDefense": 0
    },
    {
      "RequiredExp": 3574,
      "HP": 1,
      "Attack": 1,
      "Defense": 1,
      "SpecialAttack": 1,
      "SpecialDefense": 1
    },
    {
      "RequiredExp": 5216,
      "HP": 1,
      "Attack": 1,
      "Defense": 0,
      "SpecialAttack": 1,
      "SpecialDefense": 0
    },
    {
      "RequiredExp": 8132,
      "HP": 1,
      "Attack": 1,
      "Defense": 1,
      "SpecialAttack": 1,
      "SpecialDefense": 1
    },
    {
      "RequiredExp": 11051,
      "HP": 2,
      "Attack": 2,
      "Defense": 2,
      "SpecialAttack": 2,
      "SpecialDefense": 2
    },
    {
      "RequiredExp": 14323,
      "HP": 2,
      "Attack": 2,
      "Defense": 2,
      "SpecialAttack": 2,
      "SpecialDefense": 2
    },
    {
      "RequiredExp": 17600,
      "HP": 3,
      "Attack": 2,
      "Defense": 2,
      "SpecialAttack": 2,
      "SpecialDefense": 2
    },
    {
      "RequiredExp": 21238,
      "HP": 3,
      "Attack": 2,
      "Defense": 2,
      "SpecialAttack": 1,
      "SpecialDefense": 2
    },
    {
      "RequiredExp": 24879,
      "HP": 3,
      "Attack": 2,
      "Defense": 2,
      "SpecialAttack": 1,
      "SpecialDefense": 2
    },
    {
      "RequiredExp": 28523,
      "HP": 3,
      "Attack": 1,
      "Defense": 2,
      "SpecialAttack": 1,
      "SpecialDefense": 2
    },
    {
      "RequiredExp": 32194,
      "HP": 3,
      "Attack": 1,
      "Defense": 2,
      "SpecialAttack": 1,
      "SpecialDefense": 2
    },
    {
      "RequiredExp": 36447,
      "HP": 3,
      "Attack": 1,
      "Defense": 2,
      "SpecialAttack": 1,
      "SpecialDefense": 2
    },
    {
      "RequiredExp": 40704,
      "HP": 3,
      "Attack": 1,
      "Defense": 2,
      "SpecialAttack": 1,
      "SpecialDefense": 2
    },
    {
      "RequiredExp": 44965,
      "HP": 3,
      "Attack": 1,
      "Defense": 2,
      "SpecialAttack": 1,
      "SpecialDefense": 2
    },
    {
      "RequiredExp": 50391,
      "HP": 3,
      "Attack": 1,
      "Defense": 2,
      "SpecialAttack": 1,
      "SpecialDefense": 2
    },
    {
      "RequiredExp": 56992,
      "HP": 3,
      "Attack": 1,
      "Defense": 2,
      "SpecialAttack": 1,
      "SpecialDefense": 2
    },
    {
      "RequiredExp": 64175,
      "HP": 1,
      "Attack": 1,
      "Defense": 2,
      "SpecialAttack": 1,
      "SpecialDefense": 2
    },
    {
      "RequiredExp": 71939,
      "HP": 1,
      "Attack": 1,
      "Defense": 2,
      "SpecialAttack": 1,
      "SpecialDefense": 2
    },
    {
      "RequiredExp": 80286,
      "HP": 1,
      "Attack": 1,
      "Defense": 2,
      "SpecialAttack": 1,
      "SpecialDefense": 2
    },
    {
      "RequiredExp": 89214,
      "HP": 1,
      "Attack": 1,
      "Defense": 2,
      "SpecialAttack": 1,
      "SpecialDefense": 2
    },
    {
      "RequiredExp": 98725,
      "HP": 1,
      "Attack": 1,
      "Defense": 2,
      "SpecialAttack": 1,
      "SpecialDefense": 2
    },
    {
      "RequiredExp": 108817,
      "HP": 1,
      "Attack": 0,
      "Defense": 2,
      "SpecialAttack": 1,
      "SpecialDefense": 2
    },
    {
      "RequiredExp": 120664,
      "HP": 1,
      "Attack": 1,
      "Defense": 2,
      "SpecialAttack": 0,
      "SpecialDefense": 2
    },
    {
      "RequiredExp": 133093,
      "HP": 1,
      "Attack": 0,
      "Defense": 2,
      "SpecialAttack": 1,
      "SpecialDefense": 2
    },
    {
      "RequiredExp": 146103,
      "HP": 1,
      "Attack": 1,
      "Defense": 2,
      "SpecialAttack": 0,
      "SpecialDefense": 2
    },
    {
      "RequiredExp": 159695,
      "HP": 1,
      "Attack": 0,
      "Defense": 2,
      "SpecialAttack": 1,
      "SpecialDefense": 2
    },
    {
      "RequiredExp": 173869,
      "HP": 1,
      "Attack": 1,
      "Defense": 2,
      "SpecialAttack": 0,
      "SpecialDefense": 2
    },
    {
      "RequiredExp": 188625,
      "HP": 1,
      "Attack": 0,
      "Defense": 2,
      "SpecialAttack": 1,
      "SpecialDefense": 2
    },
    {
      "RequiredExp": 203963,
      "HP": 1,
      "Attack": 1,
      "Defense": 2,
      "SpecialAttack": 0,
      "SpecialDefense": 2
    },
    {
      "RequiredExp": 219882,
      "HP": 1,
      "Attack": 0,
      "Defense": 2,
      "SpecialAttack": 1,
      "SpecialDefense": 2
    },
    {
      "RequiredExp": 236384,
      "HP": 1,
      "Attack": 1,
      "Defense": 2,
      "SpecialAttack": 0,
      "SpecialDefense": 2
    },
    {
      "RequiredExp": 253467,
      "HP": 1,
      "Attack": 0,
      "Defense": 1,
      "SpecialAttack": 1,
      "SpecialDefense": 1
    },
    {
      "RequiredExp": 271133,
      "HP": 1,
      "Attack": 1,
      "Defense": 1,
      "SpecialAttack": 0,
      "SpecialDefense": 1
    },
    {
      "RequiredExp": 289962,
      "HP": 1,
      "Attack": 0,
      "Defense": 1,
      "SpecialAttack": 1,
      "SpecialDefense": 1
    },
    {
      "RequiredExp": 309955,
      "HP": 1,
      "Attack": 1,
      "Defense": 1,
      "SpecialAttack": 0,
      "SpecialDefense": 1
    },
    {
      "RequiredExp": 331111,
      "HP": 1,
      "Attack": 0,
      "Defense": 1,
      "SpecialAttack": 1,
      "SpecialDefense": 1
    },
    {
      "RequiredExp": 353431,
      "HP": 1,
      "Attack": 1,
      "Defense": 1,
      "SpecialAttack": 0,
      "SpecialDefense": 1
    },
    {
      "RequiredExp": 376915,
      "HP": 1,
      "Attack": 0,
      "Defense": 1,
      "SpecialAttack": 1,
      "SpecialDefense": 1
    },
    {
      "RequiredExp": 401563,
      "HP": 1,
      "Attack": 1,
      "Defense": 1,
      "SpecialAttack": 0,
      "SpecialDefense": 1
    },
    {
      "RequiredExp": 427374,
      "HP": 0,
      "Attack": 0,
      "Defense": 1,
      "SpecialAttack": 1,
      "SpecialDefense": 1
    },
    {
      "RequiredExp": 454349,
      "HP": 1,
      "Attack": 1,
      "Defense": 1,
      "SpecialAttack": 0,
      "SpecialDefense": 1
    },
    {
      "RequiredExp": 482488,
      "HP": 0,
      "Attack": 1,
      "Defense": 1,
      "SpecialAttack": 1,
      "SpecialDefense": 1
    },
    {
      "RequiredExp": 511587,
      "HP": 1,
      "Attack": 0,
      "Defense": 1,
      "SpecialAttack": 0,
      "SpecialDefense": 1
    },
    {
      "RequiredExp": 540692,
      "HP": 0,
      "Attack": 1,
      "Defense": 1,
      "SpecialAttack": 1,
      "SpecialDefense": 1
    },
    {
      "RequiredExp": 569803,
      "HP": 1,
      "Attack": 0,
      "Defense": 1,
      "SpecialAttack": 0,
      "SpecialDefense": 1
    },
    {
      "RequiredExp": 598919,
      "HP": 0,
      "Attack": 1,
      "Defense": 1,
      "SpecialAttack": 1,
      "SpecialDefense": 1
    },
    {
      "RequiredExp": 628042,
      "HP": 1,
      "Attack": 0,
      "Defense": 1,
      "SpecialAttack": 0,
      "SpecialDefense": 1
    },
    {
      "RequiredExp": 657170,
      "HP": 0,
      "Attack": 1,
      "Defense": 1,
      "SpecialAttack": 1,
      "SpecialDefense": 1
    },
    {
      "RequiredExp": 686304,
      "HP": 1,
      "Attack": 0,
      "Defense": 1,
      "SpecialAttack": 0,
      "SpecialDefense": 1
    },
    {
      "RequiredExp": 715444,
      "HP": 0,
      "Attack": 1,
      "Defense": 1,
      "SpecialAttack": 1,
      "SpecialDefense": 1
    },
    {
      "RequiredExp": 744590,
      "HP": 1,
      "Attack": 0,
      "Defense": 1,
      "SpecialAttack": 0,
      "SpecialDefense": 1
    },
    {
      "RequiredExp": 773741,
      "HP": 0,
      "Attack": 1,
      "Defense": 1,
      "SpecialAttack": 1,
      "SpecialDefense": 1
    },
    {
      "RequiredExp": 802898,
      "HP": 1,
      "Attack": 0,
      "Defense": 1,
      "SpecialAttack": 1,
      "SpecialDefense": 1
    },
    {
      "RequiredExp": 832062,
      "HP": 0,
      "Attack": 1,
      "Defense": 1,
      "SpecialAttack": 0,
      "SpecialDefense": 1
    },
    {
      "RequiredExp": 861231,
      "HP": 1,
      "Attack": 0,
      "Defense": 1,
      "SpecialAttack": 1,
      "SpecialDefense": 1
    },
    {
      "RequiredExp": 890405,
      "HP": 0,
      "Attack": 1,
      "Defense": 1,
      "SpecialAttack": 0,
      "SpecialDefense": 1
    },
    {
      "RequiredExp": 919586,
      "HP": 1,
      "Attack": 0,
      "Defense": 1,
      "SpecialAttack": 1,
      "SpecialDefense": 1
    },
    {
      "RequiredExp": 948772,
      "HP": 0,
      "Attack": 1,
      "Defense": 1,
      "SpecialAttack": 0,
      "SpecialDefense": 1
    },
    {
      "RequiredExp": 977964,
      "HP": 1,
      "Attack": 0,
      "Defense": 1,
      "SpecialAttack": 1,
      "SpecialDefense": 1
    },
    {
      "RequiredExp": 1007162,
      "HP": 0,
      "Attack": 1,
      "Defense": 1,
      "SpecialAttack": 0,
      "SpecialDefense": 1
    },
    {
      "RequiredExp": 1036367,
      "HP": 1,
      "Attack": 0,
      "Defense": 1,
      "SpecialAttack": 1,
      "SpecialDefense": 1
    },
    {
      "RequiredExp": 1065576,
      "HP": 0,
      "Attack": 1,
      "Defense": 1,
      "SpecialAttack": 0,
      "SpecialDefense": 1
    },
    {
      "RequiredExp": 1094792,
      "HP": 1,
      "Attack": 0,
      "Defense": 1,
      "SpecialAttack": 1,
      "SpecialDefense": 1
    },
    {
      "RequiredExp": 1124013,
      "HP": 0,
      "Attack": 1,
      "Defense": 1,
      "SpecialAttack": 0,
      "SpecialDefense": 1
    },
    {
      "RequiredExp": 1153240,
      "HP": 1,
      "Attack": 0,
      "Defense": 1,
      "SpecialAttack": 1,
      "SpecialDefense": 1
    },
    {
      "RequiredExp": 1182473,
      "HP": 0,
      "Attack": 1,
      "Defense": 1,
      "SpecialAttack": 0,
      "SpecialDefense": 1
    },
    {
      "RequiredExp": 1211712,
      "HP": 1,
      "Attack": 0,
      "Defense": 1,
      "SpecialAttack": 1,
      "SpecialDefense": 1
    },
    {
      "RequiredExp": 1240957,
      "HP": 0,
      "Attack": 1,
      "Defense": 1,
      "SpecialAttack": 0,
      "SpecialDefense": 1
    },
    {
      "RequiredExp": 1270207,
      "HP": 1,
      "Attack": 0,
      "Defense": 1,
      "SpecialAttack": 1,
      "SpecialDefense": 1
    },
    {
      "RequiredExp": 1299463,
      "HP": 0,
      "Attack": 1,
      "Defense": 1,
      "SpecialAttack": 0,
      "SpecialDefense": 1
    },
    {
      "RequiredExp": 1328725,
      "HP": 1,
      "Attack": 0,
      "Defense": 1,
      "SpecialAttack": 1,
      "SpecialDefense": 1
    },
    {
      "RequiredExp": 1357993,
      "HP": 0,
      "Attack": 1,
      "Defense": 1,
      "SpecialAttack": 0,
      "SpecialDefense": 1
    },
    {
      "RequiredExp": 1387266,
      "HP": 1,
      "Attack": 0,
      "Defense": 1,
      "SpecialAttack": 1,
      "SpecialDefense": 1
    },
    {
      "RequiredExp": 1416546,
      "HP": 0,
      "Attack": 1,
      "Defense": 1,
      "SpecialAttack": 0,
      "SpecialDefense": 1
    },
    {
      "RequiredExp": 1445832,
      "HP": 1,
      "Attack": 0,
      "Defense": 1,
      "SpecialAttack": 1,
      "SpecialDefense": 1
    },
    {
      "RequiredExp": 1475123,
      "HP": 0,
      "Attack": 1,
      "Defense": 1,
      "SpecialAttack": 0,
      "SpecialDefense": 1
    },
    {
      "RequiredExp": 1504419,
      "HP": 1,
      "Attack": 0,
      "Defense": 1,
      "SpecialAttack": 1,
      "SpecialDefense": 1
    },
    {
      "RequiredExp": 1533722,
      "HP": 0,
      "Attack": 1,
      "Defense": 1,
      "SpecialAttack": 0,
      "SpecialDefense": 1
    },
    {
      "RequiredExp": 1563031,
      "HP": 1,
      "Attack": 0,
      "Defense": 1,
      "SpecialAttack": 1,
      "SpecialDefense": 1
    },
    {
      "RequiredExp": 1592345,
      "HP": 0,
      "Attack": 1,
      "Defense": 1,
      "SpecialAttack": 0,
      "SpecialDefense": 1
    },
    {
      "RequiredExp": 1621665,
      "HP": 1,
      "Attack": 0,
      "Defense": 1,
      "SpecialAttack": 1,
      "SpecialDefense": 1
    },
    {
      "RequiredExp": 1650992,
      "HP": 0,
      "Attack": 1,
      "Defense": 1,
      "SpecialAttack": 0,
      "SpecialDefense": 1
    },
    {
      "RequiredExp": 1680323,
      "HP": 1,
      "Attack": 0,
      "Defense": 1,
      "SpecialAttack": 1,
      "SpecialDefense": 1
    },
    {
      "RequiredExp": 1709661,
      "HP": 0,
      "Attack": 1,
      "Defense": 1,
      "SpecialAttack": 0,
      "SpecialDefense": 1
    },
    {
      "RequiredExp": 1739005,
      "HP": 1,
      "Attack": 0,
      "Defense": 1,
      "SpecialAttack": 1,
      "SpecialDefense": 1
    },
    {
      "RequiredExp": 1768354,
      "HP": 0,
      "Attack": 1,
      "Defense": 1,
      "SpecialAttack": 0,
      "SpecialDefense": 1
    },
    {
      "RequiredExp": 1797709,
      "HP": 1,
      "Attack": 0,
      "Defense": 1,
      "SpecialAttack": 1,
      "SpecialDefense": 1
    },
    {
      "RequiredExp": 1827070,
      "HP": 0,
      "Attack": 1,
      "Defense": 1,
      "SpecialAttack": 0,
      "SpecialDefense": 1
    },
    {
      "RequiredExp": 1856437,
      "HP": 1,
      "Attack": 1,
      "Defense": 1,
      "SpecialAttack": 1,
      "SpecialDefense": 1
    },
    {
      "RequiredExp": 1885844,
      "HP": 1,
      "Attack": 1,
      "Defense": 1,
      "SpecialAttack": 1,
      "SpecialDefense": 1
    }
  ],
  "GenderEnitities": [
    {
      "Evolution": {
        "PreEvoDexId": 123,
        "PreEvoRawId": 123,
        "Method": 3,
        "Param1": 148,
        "Param2": 1
      },
      "Gender": 1,
      "IQGroup": 3,
      "PrimaryAbility": 67,
      "SecondaryAbility": 100,
      "BaseExpYield": 97,
      "RecruitRate": -120.0,
      "BaseStats": {
        "HP": 40,
        "Attack": 15,
        "Defense": 13,
        "SpecialAttack": 19,
        "SpecialDefense": 14
      },
      "ExclusiveItems": {
        "OneStarExclusiveA": 758,
        "OneStarExclusiveB": 759,
        "TwoStarExclusive": 760,
        "ThreeStarExclusive": 761
      }
    },
    {
      "Evolution": {
        "PreEvoDexId": 123,
        "PreEvoRawId": 723,
        "Method": 3,
        "Param1": 148,
        "Param2": 1
      },
      "Gender": 2,
      "IQGroup": 3,
      "PrimaryAbility": 67,
      "SecondaryAbility": 100,
      "BaseExpYield": 97,
      "RecruitRate": -120.0,
      "BaseStats": {
        "HP": 40,
        "Attack": 15,
        "Defense": 13,
        "SpecialAttack": 19,
        "SpecialDefense": 14
      },
      "ExclusiveItems": {
        "OneStarExclusiveA": 758,
        "OneStarExclusiveB": 759,
        "TwoStarExclusive": 760,
        "ThreeStarExclusive": 761
      }
    }
  ],
  "Movesets": [
    {
      "LevelUpMoves": [
        {
          "Level": 1,
          "MoveId": 190
        },
        {
          "Level": 1,
          "MoveId": 224
        },
        {
          "Level": 1,
          "MoveId": 510
        },
        {
          "Level": 1,
          "MoveId": 516
        },
        {
          "Level": 5,
          "MoveId": 74
        },
        {
          "Level": 9,
          "MoveId": 38
        },
        {
          "Level": 13,
          "MoveId": 314
        },
        {
          "Level": 17,
          "MoveId": 95
        },
        {
          "Level": 21,
          "MoveId": 325
        },
        {
          "Level": 25,
          "MoveId": 346
        },
        {
          "Level": 29,
          "MoveId": 81
        },
        {
          "Level": 33,
          "MoveId": 60
        },
        {
          "Level": 37,
          "MoveId": 186
        },
        {
          "Level": 41,
          "MoveId": 470
        },
        {
          "Level": 45,
          "MoveId": 491
        },
        {
          "Level": 49,
          "MoveId": 487
        },
        {
          "Level": 53,
          "MoveId": 431
        },
        {
          "Level": 57,
          "MoveId": 181
        }
      ],
      "EggMoves": null,
      "HmTmMoves": {
        "MoveIds": [
          12,
          18,
          24,
          29,
          48,
          50,
          56,
          67,
          72,
          82,
          104,
          141,
          179,
          181,
          197,
          214,
          223,
          227,
          232,
          242,
          244,
          263,
          301,
          304,
          314,
          324,
          326,
          328,
          360,
          394,
          455,
          456,
          470,
          471,
          502,
          503,
          509,
          534,
          536
        ]
      }
    },
    {
      "LevelUpMoves": [
        {
          "Level": 1,
          "MoveId": 190
        },
        {
          "Level": 1,
          "MoveId": 224
        },
        {
          "Level": 5,
          "MoveId": 74
        },
        {
          "Level": 9,
          "MoveId": 38
        },
        {
          "Level": 13,
          "MoveId": 314
        },
        {
          "Level": 17,
          "MoveId": 95
        },
        {
          "Level": 21,
          "MoveId": 325
        },
        {
          "Level": 25,
          "MoveId": 346
        },
        {
          "Level": 29,
          "MoveId": 81
        },
        {
          "Level": 33,
          "MoveId": 60
        },
        {
          "Level": 37,
          "MoveId": 186
        },
        {
          "Level": 41,
          "MoveId": 470
        },
        {
          "Level": 45,
          "MoveId": 491
        },
        {
          "Level": 49,
          "MoveId": 487
        },
        {
          "Level": 53,
          "MoveId": 431
        },
        {
          "Level": 57,
          "MoveId": 181
        }
      ],
      "EggMoves": null,
      "HmTmMoves": {
        "MoveIds": [
          12,
          18,
          24,
          29,
          48,
          50,
          56,
          67,
          72,
          82,
          104,
          141,
          179,
          181,
          197,
          214,
          223,
          227,
          232,
          242,
          244,
          263,
          301,
          304,
          314,
          324,
          326,
          328,
          360,
          394,
          455,
          456,
          470,
          471,
          502,
          503,
          509,
          534,
          536
        ]
      }
    }
  ]
}