{
  "Id": "teddiursa",
  "DexId": 216,
  "RawIndex": 243,
  "Name": "Teddiursa",
  "GameSeries": 1,
  "PrimaryType": 1,
  "SecondaryType": 0,
  "Category": "Little Bear",
  "LevelStats": [
    {
      "RequiredExp": 0,
      "HP": 0,
      "Attack": 0,
      "Defense": 0,
      "SpecialAttack": 0,
      "SpecialDefense": 0
    },
    {
      "RequiredExp": 8,
      "HP": 1,
      "Attack": 1,
      "Defense": 1,
      "SpecialAttack": 1,
      "SpecialDefense": 1
    },
    {
      "RequiredExp": 22,
      "HP": 1,
      "Attack": 1,
      "Defense": 0,
      "SpecialAttack": 1,
      "SpecialDefense": 0
    },
    {
      "RequiredExp": 38,
      "HP": 1,
      "Attack": 0,
      "Defense": 1,
      "SpecialAttack": 0,
      "SpecialDefense": 1
    },
    {
      "RequiredExp": 83,
      "HP": 1,
      "Attack": 1,
      "Defense": 0,
      "SpecialAttack": 1,
      "SpecialDefense": 0
    },
    {
      "RequiredExp": 182,
      "HP": 1,
      "Attack": 0,
      "Defense": 1,
      "SpecialAttack": 0,
      "SpecialDefense": 1
    },
    {
      "RequiredExp": 283,
      "HP": 1,
      "Attack": 1,
      "Defense": 0,
      "SpecialAttack": 1,
      "SpecialDefense": 0
    },
    {
      "RequiredExp": 530,
      "HP": 1,
      "Attack": 1,
      "Defense": 1,
      "SpecialAttack": 1,
      "SpecialDefense": 1
    },
    {
      "RequiredExp": 1069,
      "HP": 1,
      "Attack": 1,
      "Defense": 0,
      "SpecialAttack": 1,
      "SpecialDefense": 0
    },
    {
      "RequiredExp": 1612,
      "HP": 1,
      "Attack": 1,
      "Defense": 1,
      "SpecialAttack": 1,
      "SpecialDefense": 1
    },
    {
      "RequiredExp": 2464,
      "HP": 1,
      "Attack": 1,
      "Defense": 0,
      "SpecialAttack": 1,
      "SpecialDefense": 0
    },
    {
      "RequiredExp": 4547,
      "HP": 1,
      "Attack": 1,
      "Defense": 1,
      "SpecialAttack": 1,
      "SpecialDefense": 1
    },
    {
      "RequiredExp": 6635,
      "HP": 1,
      "Attack": 1,
      "Defense": 0,
      "SpecialAttack": 1,
      "SpecialDefense": 0
    },
    {
      "RequiredExp": 10345,
      "HP": 1,
      "Attack": 1,
      "Defense": 0,
      "SpecialAttack": 1,
      "SpecialDefense": 0
    },
    {
      "RequiredExp": 14058,
      "HP": 1,
      "Attack": 1,
      "Defense": 1,
      "SpecialAttack": 1,
      "SpecialDefense": 1
    },
    {
      "RequiredExp": 18221,
      "HP": 1,
      "Attack": 1,
      "Defense": 1,
      "SpecialAttack": 1,
      "SpecialDefense": 1
    },
    {
      "RequiredExp": 22390,
      "HP": 1,
      "Attack": 1,
      "Defense": 0,
      "SpecialAttack": 1,
      "SpecialDefense": 0
    },
    {
      "RequiredExp": 27018,
      "HP": 1,
      "Attack": 1,
      "Defense": 1,
      "SpecialAttack": 1,
      "SpecialDefense": 1
    },
    {
      "RequiredExp": 31650,
      "HP": 3,
      "Attack": 1,
      "Defense": 2,
      "SpecialAttack": 1,
      "SpecialDefense": 2
    },
    {
      "RequiredExp": 36285,
      "HP": 3,
      "Attack": 1,
      "Defense": 2,
      "SpecialAttack": 1,
      "SpecialDefense": 2
    },
    {
      "RequiredExp": 40956,
      "HP": 3,
      "Attack": 1,
      "Defense": 2,
      "SpecialAttack": 1,
      "SpecialDefense": 2
    },
    {
      "RequiredExp": 46366,
      "HP": 3,
      "Attack": 1,
      "Defense": 2,
      "SpecialAttack": 1,
      "SpecialDefense": 2
    },
    {
      "RequiredExp": 51781,
      "HP": 3,
      "Attack": 1,
      "Defense": 2,
      "SpecialAttack": 1,
      "SpecialDefense": 2
    },
    {
      "RequiredExp": 57202,
      "HP": 3,
      "Attack": 1,
      "Defense": 2,
      "SpecialAttack": 1,
      "SpecialDefense": 2
    },
    {
      "RequiredExp": 64105,
      "HP": 3,
      "Attack": 1,
      "Defense": 2,
      "SpecialAttack": 1,
      "SpecialDefense": 2
    },
    {
      "RequiredExp": 72503,
      "HP": 3,
      "Attack": 1,
      "Defense": 2,
      "SpecialAttack": 1,
      "SpecialDefense": 2
    },
    {
      "RequiredExp": 81641,
      "HP": 3,
      "Attack": 1,
      "Defense": 1,
      "SpecialAttack": 1,
      "SpecialDefense": 1
    },
    {
      "RequiredExp": 91518,
      "HP": 3,
      "Attack": 1,
      "Defense": 1,
      "SpecialAttack": 1,
      "SpecialDefense": 1
    },
    {
      "RequiredExp": 102136,
      "HP": 3,
      "Attack": 1,
      "Defense": 1,
      "SpecialAttack": 1,
      "SpecialDefense": 1
    },
    {
      "RequiredExp": 113495,
      "HP": 3,
      "Attack": 1,
      "Defense": 1,
      "SpecialAttack": 1,
      "SpecialDefense": 1
    },
    {
      "RequiredExp": 125594,
      "HP": 3,
      "Attack": 1,
      "Defense": 1,
      "SpecialAttack": 1,
      "SpecialDefense": 1
    },
    {
      "RequiredExp": 138433,
      "HP": 3,
      "Attack": 1,
      "Defense": 1,
      "SpecialAttack": 1,
      "SpecialDefense": 1
    },
    {
      "RequiredExp": 153504,
      "HP": 3,
      "Attack": 1,
      "Defense": 1,
      "SpecialAttack": 1,
      "SpecialDefense": 1
    },
    {
      "RequiredExp": 169315,
      "HP": 3,
      "Attack": 1,
      "Defense": 1,
      "SpecialAttack": 1,
      "SpecialDefense": 1
    },
    {
      "RequiredExp": 185866,
      "HP": 3,
      "Attack": 1,
      "Defense": 1,
      "SpecialAttack": 1,
      "SpecialDefense": 1
    },
    {
      "RequiredExp": 203157,
      "HP": 3,
      "Attack": 1,
      "Defense": 1,
      "SpecialAttack": 1,
      "SpecialDefense": 1
    },
    {
      "RequiredExp": 221189,
      "HP": 3,
      "Attack": 1,
      "Defense": 1,
      "SpecialAttack": 1,
      "SpecialDefense": 1
    },
    {
      "RequiredExp": 239960,
      "HP": 3,
      "Attack": 1,
      "Defense": 1,
      "SpecialAttack": 1,
      "SpecialDefense": 1
    },
    {
      "RequiredExp": 259473,
      "HP": 3,
      "Attack": 1,
      "Defense": 1,
      "SpecialAttack": 1,
      "SpecialDefense": 1
    },
    {
      "RequiredExp": 279725,
      "HP": 3,
      "Attack": 1,
      "Defense": 0,
      "SpecialAttack": 1,
      "SpecialDefense": 1
    },
    {
      "RequiredExp": 300718,
      "HP": 2,
      "Attack": 1,
      "Defense": 1,
      "SpecialAttack": 0,
      "SpecialDefense": 0
    },
    {
      "RequiredExp": 322451,
      "HP": 2,
      "Attack": 1,
      "Defense": 0,
      "SpecialAttack": 1,
      "SpecialDefense": 1
    },
    {
      "RequiredExp": 344923,
      "HP": 2,
      "Attack": 1,
      "Defense": 1,
      "SpecialAttack": 0,
      "SpecialDefense": 0
    },
    {
      "RequiredExp": 368877,
      "HP": 2,
      "Attack": 1,
      "Defense": 0,
      "SpecialAttack": 1,
      "SpecialDefense": 1
    },
    {
      "RequiredExp": 394311,
      "HP": 2,
      "Attack": 2,
      "Defense": 1,
      "SpecialAttack": 0,
      "SpecialDefense": 0
    },
    {
      "RequiredExp": 421225,
      "HP": 1,
      "Attack": 2,
      "Defense": 0,
      "SpecialAttack": 1,
      "SpecialDefense": 1
    },
    {
      "RequiredExp": 449620,
      "HP": 0,
      "Attack": 2,
      "Defense": 1,
      "SpecialAttack": 0,
      "SpecialDefense": 0
    },
    {
      "RequiredExp": 479495,
      "HP": 1,
      "Attack": 2,
      "Defense": 0,
      "SpecialAttack": 1,
      "SpecialDefense": 1
    },
    {
      "RequiredExp": 510851,
      "HP": 0,
      "Attack": 2,
      "Defense": 1,
      "SpecialAttack": 0,
      "SpecialDefense": 0
    },
    {
      "RequiredExp": 543687,
      "HP": 1,
      "Attack": 2,
      "Defense": 0,
      "SpecialAttack": 1,
      "SpecialDefense": 1
    },
    {
      "RequiredExp": 578004,
      "HP": 0,
      "Attack": 1,
      "Defense": 1,
      "SpecialAttack": 0,
      "SpecialDefense": 0
    },
    {
      "RequiredExp": 613801,
      "HP": 1,
      "Attack": 1,
      "Defense": 0,
      "SpecialAttack": 1,
      "SpecialDefense": 1
    },
    {
      "RequiredExp": 650820,
      "HP": 0,
      "Attack": 1,
      "Defense": 1,
      "SpecialAttack": 0,
      "SpecialDefense": 0
    },
    {
      "RequiredExp": 687845,
      "HP": 1,
      "Attack": 1,
      "Defense": 0,
      "SpecialAttack": 1,
      "SpecialDefense": 1
    },
    {
      "RequiredExp": 724879,
      "HP": 0,
      "Attack": 1,
      "Defense": 1,
      "SpecialAttack": 0,
      "SpecialDefense": 0
    },
    {
      "RequiredExp": 761920,
      "HP": 1,
      "Attack": 1,
      "Defense": 0,
      "SpecialAttack": 1,
      "SpecialDefense": 1
    },
    {
      "RequiredExp": 798968,
      "HP": 0,
      "Attack": 1,
      "Defense": 1,
      "SpecialAttack": 0,
      "SpecialDefense": 0
    },
    {
      "RequiredExp": 836024,
      "HP": 1,
      "Attack": 1,
      "Defense": 0,
      "SpecialAttack": 1,
      "SpecialDefense": 1
    },
    {
      "RequiredExp": 873087,
      "HP": 0,
      "Attack": 1,
      "Defense": 1,
      "SpecialAttack": 0,
      "SpecialDefense": 0
    },
    {
      "RequiredExp": 910158,
      "HP": 1,
      "Attack": 1,
      "Defense": 1,
      "SpecialAttack": 1,
      "SpecialDefense": 1
    },
    {
      "RequiredExp": 947235,
      "HP": 1,
      "Attack": 1,
      "Defense": 1,
      "SpecialAttack": 1,
      "SpecialDefense": 1
    },
    {
      "RequiredExp": 984320,
      "HP": 1,
      "Attack": 1,
      "Defense": 1,
      "SpecialAttack": 1,
      "SpecialDefense": 1
    },
    {
      "RequiredExp": 1021413,
      "HP": 1,
      "Attack": 1,
      "Defense": 1,
      "SpecialAttack": 1,
      "SpecialDefense": 1
    },
    {
      "RequiredExp": 1058514,
      "HP": 1,
      "Attack": 1,
      "Defense": 1,
      "SpecialAttack": 1,
      "SpecialDefense": 1
    },
    {
      "RequiredExp": 1095621,
      "HP": 1,
      "Attack": 1,
      "Defense": 1,
      "SpecialAttack": 1,
      "SpecialDefense": 1
    },
    {
      "RequiredExp": 1132736,
      "HP": 1,
      "Attack": 1,
      "Defense": 1,
      "SpecialAttack": 1,
      "SpecialDefense": 1
    },
    {
      "RequiredExp": 1169858,
      "HP": 1,
      "Attack": 1,
      "Defense": 1,
      "SpecialAttack": 1,
      "SpecialDefense": 1
    },
    {
      "RequiredExp": 1206987,
      "HP": 1,
      "Attack": 1,
      "Defense": 1,
      "SpecialAttack": 1,
      "SpecialDefense": 1
    },
    {
      "RequiredExp": 1244124,
      "HP": 1,
      "Attack": 1,
      "Defense": 1,
      "SpecialAttack": 1,
      "SpecialDefense": 1
    },
    {
      "RequiredExp": 1281269,
      "HP": 1,
      "Attack": 1,
      "Defense": 1,
      "SpecialAttack": 1,
      "SpecialDefense": 1
    },
    {
      "RequiredExp": 1318421,
      "HP": 1,
      "Attack": 1,
      "Defense": 1,
      "SpecialAttack": 1,
      "SpecialDefense": 1
    },
    {
      "RequiredExp": 1355580,
      "HP": 1,
      "Attack": 1,
      "Defense": 1,
      "SpecialAttack": 1,
      "SpecialDefense": 1
    },
    {
      "RequiredExp": 1392747,
      "HP": 1,
      "Attack": 1,
      "Defense": 1,
      "SpecialAttack": 1,
      "SpecialDefense": 1
    },
    {
      "RequiredExp": 1429921,
      "HP": 1,
      "Attack": 1,
      "Defense": 1,
      "SpecialAttack": 1,
      "SpecialDefense": 1
    },
    {
      "RequiredExp": 1467103,
      "HP": 1,
      "Attack": 1,
      "Defense": 1,
      "SpecialAttack": 1,
      "SpecialDefense": 1
    },
    {
      "RequiredExp": 1504291,
      "HP": 1,
      "Attack": 1,
      "Defense": 1,
      "SpecialAttack": 1,
      "SpecialDefense": 1
    },
    {
      "RequiredExp": 1541488,
      "HP": 1,
      "Attack": 1,
      "Defense": 1,
      "SpecialAttack": 1,
      "SpecialDefense": 1
    },
    {
      "RequiredExp": 1578692,
      "HP": 1,
      "Attack": 1,
      "Defense": 1,
      "SpecialAttack": 1,
      "SpecialDefense": 1
    },
    {
      "RequiredExp": 1615903,
      "HP": 1,
      "Attack": 1,
      "Defense": 1,
      "SpecialAttack": 1,
      "SpecialDefense": 1
    },
    {
      "RequiredExp": 1653121,
      "HP": 1,
      "Attack": 1,
      "Defense": 1,
      "SpecialAttack": 1,
      "SpecialDefense": 1
    },
    {
      "RequiredExp": 1690347,
      "HP": 1,
      "Attack": 1,
      "Defense": 1,
      "SpecialAttack": 1,
      "SpecialDefense": 1
    },
    {
      "RequiredExp": 1727580,
      "HP": 1,
      "Attack": 1,
      "Defense": 1,
      "SpecialAttack": 1,
      "SpecialDefense": 1
    },
    {
      "RequiredExp": 1764821,
      "HP": 1,
      "Attack": 1,
      "Defense": 1,
      "SpecialAttack": 1,
      "SpecialDefense": 1
    },
    {
      "RequiredExp": 1802069,
      "HP": 1,
      "Attack": 1,
      "Defense": 1,
      "SpecialAttack": 1,
      "SpecialDefense": 1
    },
    {
      "RequiredExp": 1839325,
      "HP": 1,
      "Attack": 1,
      "Defense": 1,
      "SpecialAttack": 1,
      "SpecialDefense": 1
    },
    {
      "RequiredExp": 1876588,
      "HP": 1,
      "Attack": 1,
      "Defense": 1,
      "SpecialAttack": 1,
      "SpecialDefense": 1
    },
    {
      "RequiredExp": 1913858,
      "HP": 1,
      "Attack": 1,
      "Defense": 1,
      "SpecialAttack": 1,
      "SpecialDefense": 1
    },
    {
      "RequiredExp": 1951136,
      "HP": 1,
      "Attack": 1,
      "Defense": 1,
      "SpecialAttack": 1,
      "SpecialDefense": 1
    },
    {
      "RequiredExp": 1988421,
      "HP": 1,
      "Attack": 1,
      "Defense": 1,
      "SpecialAttack": 1,
      "SpecialDefense": 1
    },
    {
      "RequiredExp": 2025713,
      "HP": 1,
      "Attack": 1,
      "Defense": 1,
      "SpecialAttack": 1,
      "SpecialDefense": 1
    },
    {
      "RequiredExp": 2063013,
      "HP": 1,
      "Attack": 1,
      "Defense": 1,
      "SpecialAttack": 1,
      "SpecialDefense": 1
    },
    {
      "RequiredExp": 2100321,
      "HP": 1,
      "Attack": 1,
      "Defense": 1,
      "SpecialAttack": 1,
      "SpecialDefense": 1
    },
    {
      "RequiredExp": 2137636,
      "HP": 1,
      "Attack": 1,
      "Defense": 1,
      "SpecialAttack": 1,
      "SpecialDefense": 1
    },
    {
      "RequiredExp": 2174958,
      "HP": 1,
      "Attack": 1,
      "Defense": 1,
      "SpecialAttack": 1,
      "SpecialDefense": 1
    },
    {
      "RequiredExp": 2212288,
      "HP": 1,
      "Attack": 1,
      "Defense": 1,
      "SpecialAttack": 1,
      "SpecialDefense": 1
    },
    {
      "RequiredExp": 2249624,
      "HP": 1,
      "Attack": 1,
      "Defense": 1,
      "SpecialAttack": 1,
      "SpecialDefense": 1
    },
    {
      "RequiredExp": 2286969,
      "HP": 1,
      "Attack": 1,
      "Defense": 1,
      "SpecialAttack": 1,
      "SpecialDefense": 1
    },
    {
      "RequiredExp": 2324320,
      "HP": 1,
      "Attack": 1,
      "Defense": 1,
      "SpecialAttack": 1,
      "SpecialDefense": 1
    },
    {
      "RequiredExp": 2361680,
      "HP": 1,
      "Attack": 1,
      "Defense": 1,
      "SpecialAttack": 1,
      "SpecialDefense": 1
    },
    {
      "RequiredExp": 2399090,
      "HP": 1,
      "Attack": 1,
      "Defense": 1,
      "SpecialAttack": 1,
      "SpecialDefense": 1
    }
  ],
  "GenderEnitities": [
    {
      "Evolution": {
        "PreEvoDexId": 0,
        "PreEvoRawId": 0,
        "Method": 0,
        "Param1": null,
        "Param2": null
      },
      "Gender": 1,
      "IQGroup": 1,
      "PrimaryAbility": 71,
      "SecondaryAbility": 109,
      "BaseExpYield": 50,
      "RecruitRate": 82.0,
      "BaseStats": {
        "HP": 27,
        "Attack": 18,
        "Defense": 11,
        "SpecialAttack": 14,
        "SpecialDefense": 11
      },
      "ExclusiveItems": {
        "OneStarExclusiveA": 814,
        "OneStarExclusiveB": 815,
        "TwoStarExclusive": 816,
        "ThreeStarExclusive": 817
      }
    },
    {
      "Evolution": {
        "PreEvoDexId": 0,
        "PreEvoRawId": 0,
        "Method": 0,
        "Param1": null,
        "Param2": null
      },
      "Gender": 2,
      "IQGroup": 1,
      "PrimaryAbility": 71,
      "SecondaryAbility": 109,
      "BaseExpYield": 50,
      "RecruitRate": 82.0,
      "BaseStats": {
        "HP": 27,
        "Attack": 18,
        "Defense": 11,
        "SpecialAttack": 14,
        "SpecialDefense": 11
      },
      "ExclusiveItems": {
        "OneStarExclusiveA": 814,
        "OneStarExclusiveB": 815,
        "TwoStarExclusive": 816,
        "ThreeStarExclusive": 817
      }
    }
  ],
  "Movesets": [
    {
      "LevelUpMoves": [
        {
          "Level": 1,
          "MoveId": 33
        },
        {
          "Level": 1,
          "MoveId": 120
        },
        {
          "Level": 1,
          "MoveId": 260
        },
        {
          "Level": 2,
          "MoveId": 287
        },
        {
          "Level": 3,
          "MoveId": 224
        },
        {
          "Level": 8,
          "MoveId": 312
        },
        {
          "Level": 15,
          "MoveId": 167
        },
        {
          "Level": 22,
          "MoveId": 10
        },
        {
          "Level": 29,
          "MoveId": 81
        },
        {
          "Level": 36,
          "MoveId": 11
        },
        {
          "Level": 43,
          "MoveId": 25
        },
        {
          "Level": 43,
          "MoveId": 232
        },
        {
          "Level": 50,
          "MoveId": 9
        },
        {
          "Level": 57,
          "MoveId": 503
        }
      ],
      "EggMoves": {
        "MoveIds": [
          3,
          33,
          51,
          62,
          90,
          140,
          170,
          203,
          227,
          325,
          440,
          491
        ]
      },
      "HmTmMoves": {
        "MoveIds": [
          8,
          12,
          18,
          22,
          24,
          29,
          30,
          48,
          50,
          56,
          67,
          72,
          73,
          75,
          104,
          118,
          172,
          179,
          181,
          197,
          214,
          223,
          227,
          232,
          263,
          265,
          284,
          301,
          304,
          324,
          326,
          328,
          360,
          394,
          471,
          472,
          476,
          503,
          534
        ]
      }
    },
    {
      "LevelUpMoves": [
        {
          "Level": 1,
          "MoveId": 33
        },
        {
          "Level": 1,
          "MoveId": 120
        },
        {
          "Level": 1,
          "MoveId": 260
        },
        {
          "Level": 2,
          "MoveId": 287
        },
        {
          "Level": 3,
          "MoveId": 224
        },
        {
          "Level": 8,
          "MoveId": 312
        },
        {
          "Level": 15,
          "MoveId": 167
        },
        {
          "Level": 22,
          "MoveId": 10
        },
        {
          "Level": 29,
          "MoveId": 81
        },
        {
          "Level": 36,
          "MoveId": 11
        },
        {
          "Level": 43,
          "MoveId": 25
        },
        {
          "Level": 43,
          "MoveId": 232
        },
        {
          "Level": 50,
          "MoveId": 9
        },
        {
          "Level": 57,
          "MoveId": 503
        }
      ],
      "EggMoves": {
        "MoveIds": [
          3,
          33,
          51,
          62,
          90,
          140,
          170,
          203,
          227,
          325,
          440,
          491
        ]
      },
      "HmTmMoves": {
        "MoveIds": [
          8,
          12,
          18,
          22,
          24,
          29,
          30,
          48,
          50,
          56,
          67,
          72,
          73,
          75,
          104,
          118,
          172,
          179,
          181,
          197,
          214,
          223,
          227,
          232,
          263,
          265,
          284,
          301,
          304,
          324,
          326,
          328,
          360,
          394,
          471,
          472,
          476,
          503,
          534
        ]
      }
    }
  ]
}