{
  "Id": "dig",
  "Name": "Dig",
  "Rarity": 0,
  "RarityParameter": null,
  "ItemCategory": 5,
  "ShortDescription": "Teaches Dig.",
  "LongDescription": "Teaches the move Dig, but won't if the Pokémon knows the move. Move gives the user a Digging status, which causes the Pokémon to charge power for 1 turn, then try a powerful attack on the next turn. You can't link this move.",
  "BuyPrice": 6500,
  "SellPrice": 250,
  "SpriteId": 8,
  "ItemId": 215,
  "Param1": 8,
  "Param2": 0,
  "Param3": 0
}